{
  "urls": [
    "https://cert.gov.ua/article/6276894",
    "https://github.com/blackorbird/APT_REPORT/blob/master/APT28/APT28%20the%20long%20hand%20of%20Russian%20interests.pdf",
    "https://harfanglab.io/en/insidethelab/compromised-routers-infrastructure-target-europe-caucasus/",
    "https://media.defense.gov/2025/May/21/2003719846/-1/-1/0/CSA_RUSSIAN_GRU_TARGET_LOGISTICS.PDF",
    "https://thehackernews.com/2024/03/apt28-hacker-group-targeting-europe.html?m=1",
    "https://www.cert.ssi.gouv.fr/uploads/CERTFR-2025-CTI-007.pdf"
  ],
  "uuid": "9233f6e6-9dd7-4b30-adaa-5baf5359d22a",
  "notes": [],
  "sources": [],
  "updated": "2025-05-22",
  "alt_names": [],
  "attribution": [
    "APT28"
  ],
  "common_name": "MASEPIE",
  "description": "",
  "library_entries": [
    "certfr:20250429:targeting:a623e6c",
    "certua:20231228:apt28:29b5be4",
    "ctr:20240129:compromised:e6b2fb6",
    "defense:20250520:russian:73a0ae3",
    "maverits:20241231:apt28:edb7884",
    "newsroom:20240318:apt28:0bb8481"
  ]
}